encrypt_encode/__init__.py
encrypt_encode/en_decode.py
encrypt_encode-2.1.dist-info/LICENSE
encrypt_encode-2.1.dist-info/METADATA
encrypt_encode-2.1.dist-info/WHEEL
encrypt_encode-2.1.dist-info/top_level.txt
encrypt_encode-2.1.dist-info/RECORD
