Metadata-Version: 2.1
Name: encrypt-encode
Version: 2.1
Summary: encrypt encode text
Home-page: https://github.com/keegang6705/encrypt_encode
Author: keegang_6705
Author-email: darunphobwi@gmail.com
License: MIT
Platform: UNKNOWN
Requires-Python: >=3.0
License-File: LICENSE
